{"456487489440579595":{"contentmessage":"none","replayMessage":"none"},"630604146256642068":{"contentmessage":"none","replayMessage":"none"},"368537351984513025":{"contentmessage":"احا","replayMessage":"عيب"},"653146548632289280":{"contentmessage":"none","replayMessage":"none"},"335645388323160064":{"contentmessage":"none","replayMessage":"none"},"172002275412279296":{"contentmessage":"none","replayMessage":"none"},"359541019836022784":{"contentmessage":"none","replayMessage":"none"},"565860579659612190":{"contentmessage":"none","replayMessage":"none"},"540456059278721024":{"contentmessage":"none","replayMessage":"none"},"654795631839412224":{"contentmessage":"none","replayMessage":"none"},"662797223922368524":{"contentmessage":"none","replayMessage":"none"},"475379654438682624":{"contentmessage":"none","replayMessage":"none"},"482209373175808003":{"contentmessage":"none","replayMessage":"none"},"282859044593598464":{"contentmessage":"none","replayMessage":"none"},"674688201570516994":{"contentmessage":"none","replayMessage":"none"},"307468229859606538":{"contentmessage":"none","replayMessage":"none"},"537622978888728587":{"contentmessage":"none","replayMessage":"none"},"279557901922729984":{"contentmessage":"none","replayMessage":"none"},"609103253656961025":{"contentmessage":"none","replayMessage":"none"},"401073929638248469":{"contentmessage":"none","replayMessage":"none"},"456031258246381589":{"contentmessage":"none","replayMessage":"none"},"671786108463611910":{"contentmessage":"none","replayMessage":"none"},"340473414479380483":{"contentmessage":"none","replayMessage":"none"},"606829090015674368":{"contentmessage":"none","replayMessage":"none"},"535827036774596628":{"contentmessage":"none","replayMessage":"none"},"567703512763334685":{"contentmessage":"none","replayMessage":"none"},"581622840143642635":{"contentmessage":"none","replayMessage":"none"},"647857488640868362":{"contentmessage":"none","replayMessage":"none"},"590702336901513217":{"contentmessage":"none","replayMessage":"none"},"593946445996883971":{"contentmessage":"none","replayMessage":"none"},"447830993978523648":{"contentmessage":"none","replayMessage":"none"},"593077706606903342":{"contentmessage":"none","replayMessage":"none"},"641268290207088670":{"contentmessage":"none","replayMessage":"none"},"655381024221429760":{"contentmessage":"none","replayMessage":"none"},"661660688560816139":{"contentmessage":"none","replayMessage":"none"},"647856061407297558":{"contentmessage":"none","replayMessage":"none"},"681558420075446326":{"contentmessage":"none","replayMessage":"none"},"682633407548882957":{"contentmessage":"none","replayMessage":"none"},"676028272655466527":{"contentmessage":"none","replayMessage":"none"},"454718366729502741":{"contentmessage":"none","replayMessage":"none"},"155149108183695360":{"contentmessage":"none","replayMessage":"none"},"475304628414578699":{"contentmessage":"none","replayMessage":"none"},"421696591787982848":{"contentmessage":"none","replayMessage":"none"},"600014116052008980":{"contentmessage":"none","replayMessage":"none"},"647138370371321867":{"contentmessage":"none","replayMessage":"none"},"682599073299300438":{"contentmessage":"none","replayMessage":"none"},"588778319126724652":{"contentmessage":"none","replayMessage":"none"},"665283217204445188":{"contentmessage":"none","replayMessage":"none"},"612810322448875528":{"contentmessage":"none","replayMessage":"none"},"667179822262386689":{"contentmessage":"none","replayMessage":"none"}}